{
    "section1": {
        "files": [
            {
                "url": "assets/background.png",
                "type": "image",
                "key": "background"
            },
            {
                "url": [
                    "src/prefabs/CroquetPlayer.js"
                ],
                "type": "scripts",
                "key": "CroquetPlayer"
            },
            {
                "url": [
                    "src/prefabs/LocalPlayer.js"
                ],
                "type": "scripts",
                "key": "LocalPlayer"
            },
            {
                "url": "assets/player.png",
                "type": "image",
                "key": "player"
            },
            {
                "url": "assets/player1.png",
                "type": "image",
                "key": "player1"
            },
            {
                "url": "assets/player2.png",
                "type": "image",
                "key": "player2"
            },
            {
                "url": [
                    "assets/audio/music/soundtrack01.mp3"
                ],
                "type": "audio",
                "key": "soundtrack01"
            }
        ]
    },
    "meta": {
        "app": "Phaser Editor 2D - Asset Pack Editor",
        "contentType": "phasereditor2d.pack.core.AssetContentType",
        "url": "https://phasereditor2d.com",
        "version": 2,
        "showAllFilesInBlocks": false
    }
}